MANIFEST.in
README.rst
README.txt
authors-transform.txt
setup.cfg
setup.py
docs/CHANGES.txt
docs/CONTRIBUTORS.txt
docs/INSTALL.txt
docs/LICENSE.GPL
docs/LICENSE.txt
netsight/__init__.py
netsight.windowsauthplugin.egg-info/PKG-INFO
netsight.windowsauthplugin.egg-info/SOURCES.txt
netsight.windowsauthplugin.egg-info/dependency_links.txt
netsight.windowsauthplugin.egg-info/entry_points.txt
netsight.windowsauthplugin.egg-info/namespace_packages.txt
netsight.windowsauthplugin.egg-info/not-zip-safe
netsight.windowsauthplugin.egg-info/requires.txt
netsight.windowsauthplugin.egg-info/top_level.txt
netsight/windowsauthplugin/README.txt
netsight/windowsauthplugin/__init__.py
netsight/windowsauthplugin/configure.zcml
netsight/windowsauthplugin/doctests.txt
netsight/windowsauthplugin/install.py
netsight/windowsauthplugin/interface.py
netsight/windowsauthplugin/krbtest.py
netsight/windowsauthplugin/plugin.py
netsight/windowsauthplugin/tests.py
netsight/windowsauthplugin/browser/__init__.py
netsight/windowsauthplugin/browser/add_plugin.zpt
netsight/windowsauthplugin/browser/configure.zcml
netsight/windowsauthplugin/browser/icon.gif
netsight/windowsauthplugin/browser/mixed.py
netsight/windowsauthplugin/profiles_mixed/__init__.py
netsight/windowsauthplugin/profiles_mixed/configure.zcml
netsight/windowsauthplugin/profiles_mixed/handlers.py
netsight/windowsauthplugin/profiles_mixed/profiles/default/browserlayer.xml
netsight/windowsauthplugin/profiles_mixed/profiles/default/jsregistry.xml
netsight/windowsauthplugin/profiles_mixed/profiles/default/metadata.xml
netsight/windowsauthplugin/profiles_mixed/profiles/default/netsight.windowsauthplugin.profiles_mixed.marker