Metadata-Version: 1.1
Name: netsight.windowsauthplugin
Version: 2.3.1
Summary: A Windows Integrated Authentication (SPNEGO/Kerberos) Plugin for PAS
Home-page: https://github.com/netsight/netsight.windowsauthplugin
Author: Matt Hamilton
Author-email: matth@netsight.co.uk
License: GPL
Platform: UNKNOWN
Classifier: Framework :: Plone
Classifier: Intended Audience :: Developers
Classifier: License :: OSI Approved :: GNU General Public License (GPL)
